phantom_hv-0.1.9.dist-info/licenses/LICENSE
phantomhv/__init__.py
phantomhv/_version.py
phantomhv/io.py
phantomhv/iostack.py
phantomhv/state_buffer.py
phantomhv/webui_components.py
phantomhv/resources/woff2/LICENSE
phantomhv/resources/woff2/SourceCodeVF-Upright.otf.woff2
phantomhv/tools/ctl.py
phantomhv/tools/webui.py
phantom_hv-0.1.9.dist-info/METADATA
phantom_hv-0.1.9.dist-info/WHEEL
phantom_hv-0.1.9.dist-info/entry_points.txt
phantom_hv-0.1.9.dist-info/top_level.txt
phantom_hv-0.1.9.dist-info/RECORD
