Metadata-Version: 2.4
Name: phantom-hv
Version: 0.1.9
Summary: Control and monitoring utilities for the Phantom HV supply developed for SWGO at MPIK.
Author-email: Felix Werner <felix.werner@mpi-hd.mpg.de>
License: MPL-2.0
Project-URL: Homepage, https://github.com/fwerner/phantom-hv/
Project-URL: Documentation, https://fwerner.github.io/phantom-hv/
Project-URL: Repository, https://github.com/fwerner/phantom-hv.git
Project-URL: Issues, https://github.com/fwerner/phantom-hv/issues
Project-URL: Changelog, https://github.com/fwerner/phantom-hv/blob/master/CHANGELOG.md
Classifier: Development Status :: 2 - Pre-Alpha
Classifier: Programming Language :: Python :: 3
Classifier: License :: OSI Approved :: Mozilla Public License 2.0 (MPL 2.0)
License-File: LICENSE
Requires-Dist: numpy
Requires-Dist: nicegui
Requires-Dist: pywebview
Requires-Dist: plotly
Requires-Dist: fastapi<=0.115.6; python_version < "3.9"
Requires-Dist: importlib_resources; python_version < "3.9"
Dynamic: license-file
